inhumate_rti/__init__.py
inhumate_rti/capability.py
inhumate_rti/channel.py
inhumate_rti/constants.py
inhumate_rti/protoscribe.py
inhumate_rti/rticlient.py
inhumate_rti/rticommand.py
inhumate_rti/rtiruntimecontrol.py
inhumate_rti/rtisocketclusterclient.py
inhumate_rti/generated/Affiliation_pb2.py
inhumate_rti/generated/Channels_pb2.py
inhumate_rti/generated/Clients_pb2.py
inhumate_rti/generated/Color_pb2.py
inhumate_rti/generated/Commands_pb2.py
inhumate_rti/generated/EntityCategory_pb2.py
inhumate_rti/generated/EntityDomain_pb2.py
inhumate_rti/generated/EntityEvent_pb2.py
inhumate_rti/generated/EntityOperation_pb2.py
inhumate_rti/generated/EntityPosition_pb2.py
inhumate_rti/generated/Entity_pb2.py
inhumate_rti/generated/Event_pb2.py
inhumate_rti/generated/GeometryOperation_pb2.py
inhumate_rti/generated/Geometry_pb2.py
inhumate_rti/generated/IdMessage_pb2.py
inhumate_rti/generated/InjectableOperation_pb2.py
inhumate_rti/generated/Injectable_pb2.py
inhumate_rti/generated/InjectionOperation_pb2.py
inhumate_rti/generated/Injection_pb2.py
inhumate_rti/generated/LVCCategory_pb2.py
inhumate_rti/generated/LaunchConfigurations_pb2.py
inhumate_rti/generated/LaunchEvent_pb2.py
inhumate_rti/generated/Logs_pb2.py
inhumate_rti/generated/MeasurementBundle_pb2.py
inhumate_rti/generated/Measurement_pb2.py
inhumate_rti/generated/Measures_pb2.py
inhumate_rti/generated/MessageBundle_pb2.py
inhumate_rti/generated/Parameter_pb2.py
inhumate_rti/generated/RuntimeControl_pb2.py
inhumate_rti/generated/RuntimeState_pb2.py
inhumate_rti/generated/Scenarios_pb2.py
inhumate_rti/proto/__init__.py
inhumate_rti-1.7.1.dist-info/licenses/LICENSE.txt
inhumate_rti-1.7.1.dist-info/METADATA
inhumate_rti-1.7.1.dist-info/WHEEL
inhumate_rti-1.7.1.dist-info/entry_points.txt
inhumate_rti-1.7.1.dist-info/top_level.txt
inhumate_rti-1.7.1.dist-info/RECORD
