Metadata-Version: 2.4
Name: inhumate-rti
Version: 1.7.1
Summary: Inhumate RTI Client
Home-page: https://github.com/inhumatesystems/rti-client
Author: Inhumate AB
Author-email: packages@inhumatesystems.com
License: Proprietary
Keywords: RTI
Classifier: Development Status :: 3 - Alpha
Classifier: Intended Audience :: Developers
Classifier: License :: OSI Approved :: Apache Software License
Classifier: Programming Language :: Python :: 3
Classifier: Programming Language :: Python :: 3.6
Classifier: Programming Language :: Python :: 3.7
License-File: LICENSE.txt
Requires-Dist: protobuf
Requires-Dist: emitter.py
Requires-Dist: websocket-client<=1.8.0,>=1.4.0
Dynamic: author
Dynamic: author-email
Dynamic: classifier
Dynamic: description
Dynamic: description-content-type
Dynamic: home-page
Dynamic: keywords
Dynamic: license
Dynamic: license-file
Dynamic: requires-dist
Dynamic: summary
